{
  "$schema": "http://cyclonedx.org/schema/bom-1.6.schema.json",
  "bomFormat": "CycloneDX",
  "specVersion": "1.6",
  "serialNumber": "urn:uuid:85641427-5ad3-402a-bb9a-530a21a1ff40",
  "version": 1,
  "metadata": {
    "timestamp": "2025-05-10T09:24:42-04:00",
    "tools": {
      "components": [
        {
          "type": "application",
          "author": "anchore",
          "name": "grype",
          "version": "0.91.2"
        }
      ]
    },
    "component": {
      "bom-ref": "ae5c5ee689cf0be5",
      "type": "container",
      "name": "alpine",
      "version": "sha256:ee1a5f755b4131874425669476dadcf5a77e1bbf9deed908d0449fa73e86adeb"
    }
  },
  "components": [
    {
      "bom-ref": "pkg:apk/alpine/alpine-baselayout@3.6.8-r1?arch=aarch64&distro=alpine-3.21.3&package-id=eb172957096b5fad",
      "type": "library",
      "publisher": "Natanael Copa <ncopa@alpinelinux.org>",
      "name": "alpine-baselayout",
      "version": "3.6.8-r1",
      "description": "Alpine base dir structure and init scripts",
      "licenses": [
        {
          "license": {
            "id": "GPL-2.0-only"
          }
        }
      ],
      "cpe": "cpe:2.3:a:alpine-baselayout:alpine-baselayout:3.6.8-r1:*:*:*:*:*:*:*",
      "purl": "pkg:apk/alpine/alpine-baselayout@3.6.8-r1?arch=aarch64&distro=alpine-3.21.3",
      "externalReferences": [
        {
          "url": "https://git.alpinelinux.org/cgit/aports/tree/main/alpine-baselayout",
          "type": "distribution"
        }
      ],
      "properties": [
        {
          "name": "syft:package:foundBy",
          "value": "apk-db-cataloger"
        },
        {
          "name": "syft:package:type",
          "value": "apk"
        },
        {
          "name": "syft:package:metadataType",
          "value": "apk-db-entry"
        },
        {
          "name": "syft:cpe23",
          "value": "cpe:2.3:a:alpine-baselayout:alpine_baselayout:3.6.8-r1:*:*:*:*:*:*:*"
        },
        {
          "name": "syft:cpe23",
          "value": "cpe:2.3:a:alpine_baselayout:alpine-baselayout:3.6.8-r1:*:*:*:*:*:*:*"
        },
        {
          "name": "syft:cpe23",
          "value": "cpe:2.3:a:alpine_baselayout:alpine_baselayout:3.6.8-r1:*:*:*:*:*:*:*"
        },
        {
          "name": "syft:cpe23",
          "value": "cpe:2.3:a:alpine:alpine-baselayout:3.6.8-r1:*:*:*:*:*:*:*"
        },
        {
          "name": "syft:cpe23",
          "value": "cpe:2.3:a:alpine:alpine_baselayout:3.6.8-r1:*:*:*:*:*:*:*"
        },
        {
          "name": "syft:location:0:layerID",
          "value": "sha256:a16e98724c05975ee8c40d8fe389c3481373d34ab20a1cf52ea2accc43f71f4c"
        },
        {
          "name": "syft:location:0:path",
          "value": "/lib/apk/db/installed"
        },
        {
          "name": "syft:metadata:gitCommitOfApkPort",
          "value": "5f0cd7890349e7fe11128478ac506c709805224d"
        },
        {
          "name": "syft:metadata:installedSize",
          "value": "6532"
        },
        {
          "name": "syft:metadata:originPackage",
          "value": "alpine-baselayout"
        },
        {
          "name": "syft:metadata:pullChecksum",
          "value": "Q1fMzOBGrN5A2tRfD+hq90EexboUQ="
        },
        {
          "name": "syft:metadata:pullDependencies:0",
          "value": "alpine-baselayout-data=3.6.8-r1"
        },
        {
          "name": "syft:metadata:pullDependencies:1",
          "value": "/bin/sh"
        },
        {
          "name": "syft:metadata:size",
          "value": "8289"
        }
      ]
    },
    {
      "bom-ref": "pkg:apk/alpine/alpine-baselayout-data@3.6.8-r1?arch=aarch64&distro=alpine-3.21.3&package-id=310baff175e0e857&upstream=alpine-baselayout",
      "type": "library",
      "publisher": "Natanael Copa <ncopa@alpinelinux.org>",
      "name": "alpine-baselayout-data",
      "version": "3.6.8-r1",
      "description": "Alpine base dir structure and init scripts",
      "licenses": [
        {
          "license": {
            "id": "GPL-2.0-only"
          }
        }
      ],
      "cpe": "cpe:2.3:a:alpine-baselayout-data:alpine-baselayout-data:3.6.8-r1:*:*:*:*:*:*:*",
      "purl": "pkg:apk/alpine/alpine-baselayout-data@3.6.8-r1?arch=aarch64&distro=alpine-3.21.3&upstream=alpine-baselayout",
      "externalReferences": [
        {
          "url": "https://git.alpinelinux.org/cgit/aports/tree/main/alpine-baselayout",
          "type": "distribution"
        }
      ],
      "properties": [
        {
          "name": "syft:package:foundBy",
          "value": "apk-db-cataloger"
        },
        {
          "name": "syft:package:type",
          "value": "apk"
        },
        {
          "name": "syft:package:metadataType",
          "value": "apk-db-entry"
        },
        {
          "name": "syft:cpe23",
          "value": "cpe:2.3:a:alpine-baselayout-data:alpine_baselayout_data:3.6.8-r1:*:*:*:*:*:*:*"
        },
        {
          "name": "syft:cpe23",
          "value": "cpe:2.3:a:alpine_baselayout_data:alpine-baselayout-data:3.6.8-r1:*:*:*:*:*:*:*"
        },
        {
          "name": "syft:cpe23",
          "value": "cpe:2.3:a:alpine_baselayout_data:alpine_baselayout_data:3.6.8-r1:*:*:*:*:*:*:*"
        },
        {
          "name": "syft:cpe23",
          "value": "cpe:2.3:a:alpine-baselayout:alpine-baselayout-data:3.6.8-r1:*:*:*:*:*:*:*"
        },
        {
          "name": "syft:cpe23",
          "value": "cpe:2.3:a:alpine-baselayout:alpine_baselayout_data:3.6.8-r1:*:*:*:*:*:*:*"
        },
        {
          "name": "syft:cpe23",
          "value": "cpe:2.3:a:alpine_baselayout:alpine-baselayout-data:3.6.8-r1:*:*:*:*:*:*:*"
        },
        {
          "name": "syft:cpe23",
          "value": "cpe:2.3:a:alpine_baselayout:alpine_baselayout_data:3.6.8-r1:*:*:*:*:*:*:*"
        },
        {
          "name": "syft:cpe23",
          "value": "cpe:2.3:a:alpine:alpine-baselayout-data:3.6.8-r1:*:*:*:*:*:*:*"
        },
        {
          "name": "syft:cpe23",
          "value": "cpe:2.3:a:alpine:alpine_baselayout_data:3.6.8-r1:*:*:*:*:*:*:*"
        },
        {
          "name": "syft:location:0:layerID",
          "value": "sha256:a16e98724c05975ee8c40d8fe389c3481373d34ab20a1cf52ea2accc43f71f4c"
        },
        {
          "name": "syft:location:0:path",
          "value": "/lib/apk/db/installed"
        },
        {
          "name": "syft:metadata:gitCommitOfApkPort",
          "value": "5f0cd7890349e7fe11128478ac506c709805224d"
        },
        {
          "name": "syft:metadata:installedSize",
          "value": "19034"
        },
        {
          "name": "syft:metadata:originPackage",
          "value": "alpine-baselayout"
        },
        {
          "name": "syft:metadata:pullChecksum",
          "value": "Q1YluBoF1dbOwSXQzQPPjP8CnKLb0="
        },
        {
          "name": "syft:metadata:size",
          "value": "10708"
        }
      ]
    },
    {
      "bom-ref": "pkg:apk/alpine/alpine-keys@2.5-r0?arch=aarch64&distro=alpine-3.21.3&package-id=735292f63d85ad1b",
      "type": "library",
      "publisher": "Natanael Copa <ncopa@alpinelinux.org>",
      "name": "alpine-keys",
      "version": "2.5-r0",
      "description": "Public keys for Alpine Linux packages",
      "licenses": [
        {
          "license": {
            "id": "MIT"
          }
        }
      ],
      "cpe": "cpe:2.3:a:alpine-keys:alpine-keys:2.5-r0:*:*:*:*:*:*:*",
      "purl": "pkg:apk/alpine/alpine-keys@2.5-r0?arch=aarch64&distro=alpine-3.21.3",
      "externalReferences": [
        {
          "url": "https://alpinelinux.org",
          "type": "distribution"
        }
      ],
      "properties": [
        {
          "name": "syft:package:foundBy",
          "value": "apk-db-cataloger"
        },
        {
          "name": "syft:package:type",
          "value": "apk"
        },
        {
          "name": "syft:package:metadataType",
          "value": "apk-db-entry"
        },
        {
          "name": "syft:cpe23",
          "value": "cpe:2.3:a:alpine-keys:alpine_keys:2.5-r0:*:*:*:*:*:*:*"
        },
        {
          "name": "syft:cpe23",
          "value": "cpe:2.3:a:alpine_keys:alpine-keys:2.5-r0:*:*:*:*:*:*:*"
        },
        {
          "name": "syft:cpe23",
          "value": "cpe:2.3:a:alpine_keys:alpine_keys:2.5-r0:*:*:*:*:*:*:*"
        },
        {
          "name": "syft:cpe23",
          "value": "cpe:2.3:a:alpine:alpine-keys:2.5-r0:*:*:*:*:*:*:*"
        },
        {
          "name": "syft:cpe23",
          "value": "cpe:2.3:a:alpine:alpine_keys:2.5-r0:*:*:*:*:*:*:*"
        },
        {
          "name": "syft:location:0:layerID",
          "value": "sha256:a16e98724c05975ee8c40d8fe389c3481373d34ab20a1cf52ea2accc43f71f4c"
        },
        {
          "name": "syft:location:0:path",
          "value": "/lib/apk/db/installed"
        },
        {
          "name": "syft:metadata:gitCommitOfApkPort",
          "value": "6d473fb38effb2389f567b29fb7eb27039b3a279"
        },
        {
          "name": "syft:metadata:installedSize",
          "value": "14561"
        },
        {
          "name": "syft:metadata:originPackage",
          "value": "alpine-keys"
        },
        {
          "name": "syft:metadata:pullChecksum",
          "value": "Q1MchWO9rd+xBzdNDZBiwL1Tg9/aU="
        },
        {
          "name": "syft:metadata:size",
          "value": "13869"
        }
      ]
    },
    {
      "bom-ref": "pkg:apk/alpine/alpine-release@3.21.3-r0?arch=aarch64&distro=alpine-3.21.3&package-id=c2770f4444533708&upstream=alpine-base",
      "type": "library",
      "publisher": "Natanael Copa <ncopa@alpinelinux.org>",
      "name": "alpine-release",
      "version": "3.21.3-r0",
      "description": "Alpine release data",
      "licenses": [
        {
          "license": {
            "id": "MIT"
          }
        }
      ],
      "cpe": "cpe:2.3:a:alpine-release:alpine-release:3.21.3-r0:*:*:*:*:*:*:*",
      "purl": "pkg:apk/alpine/alpine-release@3.21.3-r0?arch=aarch64&distro=alpine-3.21.3&upstream=alpine-base",
      "externalReferences": [
        {
          "url": "https://alpinelinux.org",
          "type": "distribution"
        }
      ],
      "properties": [
        {
          "name": "syft:package:foundBy",
          "value": "apk-db-cataloger"
        },
        {
          "name": "syft:package:type",
          "value": "apk"
        },
        {
          "name": "syft:package:metadataType",
          "value": "apk-db-entry"
        },
        {
          "name": "syft:cpe23",
          "value": "cpe:2.3:a:alpine-release:alpine_release:3.21.3-r0:*:*:*:*:*:*:*"
        },
        {
          "name": "syft:cpe23",
          "value": "cpe:2.3:a:alpine_release:alpine-release:3.21.3-r0:*:*:*:*:*:*:*"
        },
        {
          "name": "syft:cpe23",
          "value": "cpe:2.3:a:alpine_release:alpine_release:3.21.3-r0:*:*:*:*:*:*:*"
        },
        {
          "name": "syft:cpe23",
          "value": "cpe:2.3:a:alpine:alpine-release:3.21.3-r0:*:*:*:*:*:*:*"
        },
        {
          "name": "syft:cpe23",
          "value": "cpe:2.3:a:alpine:alpine_release:3.21.3-r0:*:*:*:*:*:*:*"
        },
        {
          "name": "syft:location:0:layerID",
          "value": "sha256:a16e98724c05975ee8c40d8fe389c3481373d34ab20a1cf52ea2accc43f71f4c"
        },
        {
          "name": "syft:location:0:path",
          "value": "/lib/apk/db/installed"
        },
        {
          "name": "syft:metadata:gitCommitOfApkPort",
          "value": "899c70c801638ce9aea29a822aaa07a1488efa15"
        },
        {
          "name": "syft:metadata:installedSize",
          "value": "346"
        },
        {
          "name": "syft:metadata:originPackage",
          "value": "alpine-base"
        },
        {
          "name": "syft:metadata:pullChecksum",
          "value": "Q1fnZHIR6WHZWJ7LVYreAUNOR3tG8="
        },
        {
          "name": "syft:metadata:pullDependencies:0",
          "value": "alpine-keys"
        },
        {
          "name": "syft:metadata:size",
          "value": "2021"
        }
      ]
    },
    {
      "bom-ref": "pkg:apk/alpine/apk-tools@2.14.6-r3?arch=aarch64&distro=alpine-3.21.3&package-id=34599c1544d9cb19",
      "type": "library",
      "publisher": "Natanael Copa <ncopa@alpinelinux.org>",
      "name": "apk-tools",
      "version": "2.14.6-r3",
      "description": "Alpine Package Keeper - package manager for alpine",
      "licenses": [
        {
          "license": {
            "id": "GPL-2.0-only"
          }
        }
      ],
      "cpe": "cpe:2.3:a:apk-tools:apk-tools:2.14.6-r3:*:*:*:*:*:*:*",
      "purl": "pkg:apk/alpine/apk-tools@2.14.6-r3?arch=aarch64&distro=alpine-3.21.3",
      "externalReferences": [
        {
          "url": "https://gitlab.alpinelinux.org/alpine/apk-tools",
          "type": "distribution"
        }
      ],
      "properties": [
        {
          "name": "syft:package:foundBy",
          "value": "apk-db-cataloger"
        },
        {
          "name": "syft:package:type",
          "value": "apk"
        },
        {
          "name": "syft:package:metadataType",
          "value": "apk-db-entry"
        },
        {
          "name": "syft:cpe23",
          "value": "cpe:2.3:a:apk-tools:apk_tools:2.14.6-r3:*:*:*:*:*:*:*"
        },
        {
          "name": "syft:cpe23",
          "value": "cpe:2.3:a:apk_tools:apk-tools:2.14.6-r3:*:*:*:*:*:*:*"
        },
        {
          "name": "syft:cpe23",
          "value": "cpe:2.3:a:apk_tools:apk_tools:2.14.6-r3:*:*:*:*:*:*:*"
        },
        {
          "name": "syft:cpe23",
          "value": "cpe:2.3:a:apk:apk-tools:2.14.6-r3:*:*:*:*:*:*:*"
        },
        {
          "name": "syft:cpe23",
          "value": "cpe:2.3:a:apk:apk_tools:2.14.6-r3:*:*:*:*:*:*:*"
        },
        {
          "name": "syft:location:0:layerID",
          "value": "sha256:a16e98724c05975ee8c40d8fe389c3481373d34ab20a1cf52ea2accc43f71f4c"
        },
        {
          "name": "syft:location:0:path",
          "value": "/lib/apk/db/installed"
        },
        {
          "name": "syft:metadata:gitCommitOfApkPort",
          "value": "41847d6ccff08940b5bf1ba0d6005e95897039f9"
        },
        {
          "name": "syft:metadata:installedSize",
          "value": "269592"
        },
        {
          "name": "syft:metadata:originPackage",
          "value": "apk-tools"
        },
        {
          "name": "syft:metadata:provides:0",
          "value": "so:libapk.so.2.14.0=2.14.0"
        },
        {
          "name": "syft:metadata:provides:1",
          "value": "cmd:apk=2.14.6-r3"
        },
        {
          "name": "syft:metadata:pullChecksum",
          "value": "Q1CkP9a3awut9Uv8Wj9F0CqEKo7YM="
        },
        {
          "name": "syft:metadata:pullDependencies:0",
          "value": "musl>=1.2.3_git20230424"
        },
        {
          "name": "syft:metadata:pullDependencies:1",
          "value": "ca-certificates-bundle"
        },
        {
          "name": "syft:metadata:pullDependencies:2",
          "value": "so:libc.musl-aarch64.so.1"
        },
        {
          "name": "syft:metadata:pullDependencies:3",
          "value": "so:libcrypto.so.3"
        },
        {
          "name": "syft:metadata:pullDependencies:4",
          "value": "so:libssl.so.3"
        },
        {
          "name": "syft:metadata:pullDependencies:5",
          "value": "so:libz.so.1"
        },
        {
          "name": "syft:metadata:size",
          "value": "125291"
        }
      ]
    },
    {
      "bom-ref": "pkg:apk/alpine/busybox@1.37.0-r12?arch=aarch64&distro=alpine-3.21.3&package-id=59022883e79a5e6e",
      "type": "library",
      "publisher": "Sören Tempel <soeren+alpine@soeren-tempel.net>",
      "name": "busybox",
      "version": "1.37.0-r12",
      "description": "Size optimized toolbox of many common UNIX utilities",
      "licenses": [
        {
          "license": {
            "id": "GPL-2.0-only"
          }
        }
      ],
      "cpe": "cpe:2.3:a:busybox:busybox:1.37.0-r12:*:*:*:*:*:*:*",
      "purl": "pkg:apk/alpine/busybox@1.37.0-r12?arch=aarch64&distro=alpine-3.21.3",
      "externalReferences": [
        {
          "url": "https://busybox.net/",
          "type": "distribution"
        }
      ],
      "properties": [
        {
          "name": "syft:package:foundBy",
          "value": "apk-db-cataloger"
        },
        {
          "name": "syft:package:type",
          "value": "apk"
        },
        {
          "name": "syft:package:metadataType",
          "value": "apk-db-entry"
        },
        {
          "name": "syft:location:0:layerID",
          "value": "sha256:a16e98724c05975ee8c40d8fe389c3481373d34ab20a1cf52ea2accc43f71f4c"
        },
        {
          "name": "syft:location:0:path",
          "value": "/lib/apk/db/installed"
        },
        {
          "name": "syft:metadata:gitCommitOfApkPort",
          "value": "9c49608930ef6a9936750e9e39edec56b3db9cd5"
        },
        {
          "name": "syft:metadata:installedSize",
          "value": "927849"
        },
        {
          "name": "syft:metadata:originPackage",
          "value": "busybox"
        },
        {
          "name": "syft:metadata:provides:0",
          "value": "cmd:busybox=1.37.0-r12"
        },
        {
          "name": "syft:metadata:pullChecksum",
          "value": "Q14x7cdyQoSZWgyJG95ddz1MoV8uw="
        },
        {
          "name": "syft:metadata:pullDependencies:0",
          "value": "so:libc.musl-aarch64.so.1"
        },
        {
          "name": "syft:metadata:size",
          "value": "524776"
        }
      ]
    },
    {
      "bom-ref": "pkg:apk/alpine/busybox-binsh@1.37.0-r12?arch=aarch64&distro=alpine-3.21.3&package-id=48085e7886725464&upstream=busybox",
      "type": "library",
      "publisher": "Sören Tempel <soeren+alpine@soeren-tempel.net>",
      "name": "busybox-binsh",
      "version": "1.37.0-r12",
      "description": "busybox ash /bin/sh",
      "licenses": [
        {
          "license": {
            "id": "GPL-2.0-only"
          }
        }
      ],
      "cpe": "cpe:2.3:a:busybox-binsh:busybox-binsh:1.37.0-r12:*:*:*:*:*:*:*",
      "purl": "pkg:apk/alpine/busybox-binsh@1.37.0-r12?arch=aarch64&distro=alpine-3.21.3&upstream=busybox",
      "externalReferences": [
        {
          "url": "https://busybox.net/",
          "type": "distribution"
        }
      ],
      "properties": [
        {
          "name": "syft:package:foundBy",
          "value": "apk-db-cataloger"
        },
        {
          "name": "syft:package:type",
          "value": "apk"
        },
        {
          "name": "syft:package:metadataType",
          "value": "apk-db-entry"
        },
        {
          "name": "syft:cpe23",
          "value": "cpe:2.3:a:busybox-binsh:busybox_binsh:1.37.0-r12:*:*:*:*:*:*:*"
        },
        {
          "name": "syft:cpe23",
          "value": "cpe:2.3:a:busybox_binsh:busybox-binsh:1.37.0-r12:*:*:*:*:*:*:*"
        },
        {
          "name": "syft:cpe23",
          "value": "cpe:2.3:a:busybox_binsh:busybox_binsh:1.37.0-r12:*:*:*:*:*:*:*"
        },
        {
          "name": "syft:cpe23",
          "value": "cpe:2.3:a:busybox:busybox-binsh:1.37.0-r12:*:*:*:*:*:*:*"
        },
        {
          "name": "syft:cpe23",
          "value": "cpe:2.3:a:busybox:busybox_binsh:1.37.0-r12:*:*:*:*:*:*:*"
        },
        {
          "name": "syft:location:0:layerID",
          "value": "sha256:a16e98724c05975ee8c40d8fe389c3481373d34ab20a1cf52ea2accc43f71f4c"
        },
        {
          "name": "syft:location:0:path",
          "value": "/lib/apk/db/installed"
        },
        {
          "name": "syft:metadata:gitCommitOfApkPort",
          "value": "9c49608930ef6a9936750e9e39edec56b3db9cd5"
        },
        {
          "name": "syft:metadata:installedSize",
          "value": "1"
        },
        {
          "name": "syft:metadata:originPackage",
          "value": "busybox"
        },
        {
          "name": "syft:metadata:provides:0",
          "value": "/bin/sh"
        },
        {
          "name": "syft:metadata:provides:1",
          "value": "cmd:sh=1.37.0-r12"
        },
        {
          "name": "syft:metadata:pullChecksum",
          "value": "Q1tKnb2Vs5sOjTMGEeq2fmONarBzA="
        },
        {
          "name": "syft:metadata:pullDependencies:0",
          "value": "busybox=1.37.0-r12"
        },
        {
          "name": "syft:metadata:size",
          "value": "1487"
        }
      ]
    },
    {
      "bom-ref": "pkg:apk/alpine/ca-certificates-bundle@20241121-r1?arch=aarch64&distro=alpine-3.21.3&package-id=c220c2f0a7efb6df&upstream=ca-certificates",
      "type": "library",
      "publisher": "Natanael Copa <ncopa@alpinelinux.org>",
      "name": "ca-certificates-bundle",
      "version": "20241121-r1",
      "description": "Pre generated bundle of Mozilla certificates",
      "licenses": [
        {
          "expression": "MPL-2.0 AND MIT"
        }
      ],
      "cpe": "cpe:2.3:a:ca-certificates-bundle:ca-certificates-bundle:20241121-r1:*:*:*:*:*:*:*",
      "purl": "pkg:apk/alpine/ca-certificates-bundle@20241121-r1?arch=aarch64&distro=alpine-3.21.3&upstream=ca-certificates",
      "externalReferences": [
        {
          "url": "https://www.mozilla.org/en-US/about/governance/policies/security-group/certs/",
          "type": "distribution"
        }
      ],
      "properties": [
        {
          "name": "syft:package:foundBy",
          "value": "apk-db-cataloger"
        },
        {
          "name": "syft:package:type",
          "value": "apk"
        },
        {
          "name": "syft:package:metadataType",
          "value": "apk-db-entry"
        },
        {
          "name": "syft:cpe23",
          "value": "cpe:2.3:a:ca-certificates-bundle:ca_certificates_bundle:20241121-r1:*:*:*:*:*:*:*"
        },
        {
          "name": "syft:cpe23",
          "value": "cpe:2.3:a:ca_certificates_bundle:ca-certificates-bundle:20241121-r1:*:*:*:*:*:*:*"
        },
        {
          "name": "syft:cpe23",
          "value": "cpe:2.3:a:ca_certificates_bundle:ca_certificates_bundle:20241121-r1:*:*:*:*:*:*:*"
        },
        {
          "name": "syft:cpe23",
          "value": "cpe:2.3:a:ca-certificates:ca-certificates-bundle:20241121-r1:*:*:*:*:*:*:*"
        },
        {
          "name": "syft:cpe23",
          "value": "cpe:2.3:a:ca-certificates:ca_certificates_bundle:20241121-r1:*:*:*:*:*:*:*"
        },
        {
          "name": "syft:cpe23",
          "value": "cpe:2.3:a:ca_certificates:ca-certificates-bundle:20241121-r1:*:*:*:*:*:*:*"
        },
        {
          "name": "syft:cpe23",
          "value": "cpe:2.3:a:ca_certificates:ca_certificates_bundle:20241121-r1:*:*:*:*:*:*:*"
        },
        {
          "name": "syft:cpe23",
          "value": "cpe:2.3:a:mozilla:ca-certificates-bundle:20241121-r1:*:*:*:*:*:*:*"
        },
        {
          "name": "syft:cpe23",
          "value": "cpe:2.3:a:mozilla:ca_certificates_bundle:20241121-r1:*:*:*:*:*:*:*"
        },
        {
          "name": "syft:cpe23",
          "value": "cpe:2.3:a:ca:ca-certificates-bundle:20241121-r1:*:*:*:*:*:*:*"
        },
        {
          "name": "syft:cpe23",
          "value": "cpe:2.3:a:ca:ca_certificates_bundle:20241121-r1:*:*:*:*:*:*:*"
        },
        {
          "name": "syft:location:0:layerID",
          "value": "sha256:a16e98724c05975ee8c40d8fe389c3481373d34ab20a1cf52ea2accc43f71f4c"
        },
        {
          "name": "syft:location:0:path",
          "value": "/lib/apk/db/installed"
        },
        {
          "name": "syft:metadata:gitCommitOfApkPort",
          "value": "707ff77afebd8ef5bd60f3a5dd1b08f8c480f531"
        },
        {
          "name": "syft:metadata:installedSize",
          "value": "222597"
        },
        {
          "name": "syft:metadata:originPackage",
          "value": "ca-certificates"
        },
        {
          "name": "syft:metadata:provides:0",
          "value": "ca-certificates-cacert=20241121-r1"
        },
        {
          "name": "syft:metadata:pullChecksum",
          "value": "Q1u+wb12YGwjm/zk/SMQPFkeoY5rU="
        },
        {
          "name": "syft:metadata:size",
          "value": "130916"
        }
      ]
    },
    {
      "bom-ref": "pkg:apk/alpine/libcrypto3@3.3.3-r0?arch=aarch64&distro=alpine-3.21.3&package-id=de0a6f96a830ce94&upstream=openssl",
      "type": "library",
      "publisher": "Natanael Copa <ncopa@alpinelinux.org>",
      "name": "libcrypto3",
      "version": "3.3.3-r0",
      "description": "Crypto library from openssl",
      "licenses": [
        {
          "license": {
            "id": "Apache-2.0"
          }
        }
      ],
      "cpe": "cpe:2.3:a:libcrypto3:libcrypto3:3.3.3-r0:*:*:*:*:*:*:*",
      "purl": "pkg:apk/alpine/libcrypto3@3.3.3-r0?arch=aarch64&distro=alpine-3.21.3&upstream=openssl",
      "externalReferences": [
        {
          "url": "https://www.openssl.org/",
          "type": "distribution"
        }
      ],
      "properties": [
        {
          "name": "syft:package:foundBy",
          "value": "apk-db-cataloger"
        },
        {
          "name": "syft:package:type",
          "value": "apk"
        },
        {
          "name": "syft:package:metadataType",
          "value": "apk-db-entry"
        },
        {
          "name": "syft:cpe23",
          "value": "cpe:2.3:a:libcrypto3:libcrypto:3.3.3-r0:*:*:*:*:*:*:*"
        },
        {
          "name": "syft:cpe23",
          "value": "cpe:2.3:a:libcrypto:libcrypto3:3.3.3-r0:*:*:*:*:*:*:*"
        },
        {
          "name": "syft:cpe23",
          "value": "cpe:2.3:a:libcrypto:libcrypto:3.3.3-r0:*:*:*:*:*:*:*"
        },
        {
          "name": "syft:location:0:layerID",
          "value": "sha256:a16e98724c05975ee8c40d8fe389c3481373d34ab20a1cf52ea2accc43f71f4c"
        },
        {
          "name": "syft:location:0:path",
          "value": "/lib/apk/db/installed"
        },
        {
          "name": "syft:metadata:gitCommitOfApkPort",
          "value": "ddbf4a43b534e1e2da4ccb72bdc4ffcd9b85ce03"
        },
        {
          "name": "syft:metadata:installedSize",
          "value": "4567672"
        },
        {
          "name": "syft:metadata:originPackage",
          "value": "openssl"
        },
        {
          "name": "syft:metadata:provides:0",
          "value": "so:libcrypto.so.3=3"
        },
        {
          "name": "syft:metadata:pullChecksum",
          "value": "Q1sL2FMKlyrvWwx/5c11siZeR/v4g="
        },
        {
          "name": "syft:metadata:pullDependencies:0",
          "value": "so:libc.musl-aarch64.so.1"
        },
        {
          "name": "syft:metadata:size",
          "value": "2147557"
        }
      ]
    },
    {
      "bom-ref": "pkg:apk/alpine/libssl3@3.3.3-r0?arch=aarch64&distro=alpine-3.21.3&package-id=9863a120116129b2&upstream=openssl",
      "type": "library",
      "publisher": "Natanael Copa <ncopa@alpinelinux.org>",
      "name": "libssl3",
      "version": "3.3.3-r0",
      "description": "SSL shared libraries",
      "licenses": [
        {
          "license": {
            "id": "Apache-2.0"
          }
        }
      ],
      "cpe": "cpe:2.3:a:libssl3:libssl3:3.3.3-r0:*:*:*:*:*:*:*",
      "purl": "pkg:apk/alpine/libssl3@3.3.3-r0?arch=aarch64&distro=alpine-3.21.3&upstream=openssl",
      "externalReferences": [
        {
          "url": "https://www.openssl.org/",
          "type": "distribution"
        }
      ],
      "properties": [
        {
          "name": "syft:package:foundBy",
          "value": "apk-db-cataloger"
        },
        {
          "name": "syft:package:type",
          "value": "apk"
        },
        {
          "name": "syft:package:metadataType",
          "value": "apk-db-entry"
        },
        {
          "name": "syft:cpe23",
          "value": "cpe:2.3:a:libssl3:libssl:3.3.3-r0:*:*:*:*:*:*:*"
        },
        {
          "name": "syft:cpe23",
          "value": "cpe:2.3:a:libssl:libssl3:3.3.3-r0:*:*:*:*:*:*:*"
        },
        {
          "name": "syft:cpe23",
          "value": "cpe:2.3:a:libssl:libssl:3.3.3-r0:*:*:*:*:*:*:*"
        },
        {
          "name": "syft:location:0:layerID",
          "value": "sha256:a16e98724c05975ee8c40d8fe389c3481373d34ab20a1cf52ea2accc43f71f4c"
        },
        {
          "name": "syft:location:0:path",
          "value": "/lib/apk/db/installed"
        },
        {
          "name": "syft:metadata:gitCommitOfApkPort",
          "value": "ddbf4a43b534e1e2da4ccb72bdc4ffcd9b85ce03"
        },
        {
          "name": "syft:metadata:installedSize",
          "value": "868080"
        },
        {
          "name": "syft:metadata:originPackage",
          "value": "openssl"
        },
        {
          "name": "syft:metadata:provides:0",
          "value": "so:libssl.so.3=3"
        },
        {
          "name": "syft:metadata:pullChecksum",
          "value": "Q1BGirx6NmgyKc3o3HyW/IjhxiSig="
        },
        {
          "name": "syft:metadata:pullDependencies:0",
          "value": "libcrypto3=3.3.3-r0"
        },
        {
          "name": "syft:metadata:pullDependencies:1",
          "value": "so:libc.musl-aarch64.so.1"
        },
        {
          "name": "syft:metadata:pullDependencies:2",
          "value": "so:libcrypto.so.3"
        },
        {
          "name": "syft:metadata:size",
          "value": "348623"
        }
      ]
    },
    {
      "bom-ref": "pkg:apk/alpine/musl@1.2.5-r9?arch=aarch64&distro=alpine-3.21.3&package-id=462870b7d92984af",
      "type": "library",
      "publisher": "Natanael Copa <ncopa@alpinelinux.org>",
      "name": "musl",
      "version": "1.2.5-r9",
      "description": "the musl c library (libc) implementation",
      "licenses": [
        {
          "license": {
            "id": "MIT"
          }
        }
      ],
      "cpe": "cpe:2.3:a:musl-libc:musl:1.2.5-r9:*:*:*:*:*:*:*",
      "purl": "pkg:apk/alpine/musl@1.2.5-r9?arch=aarch64&distro=alpine-3.21.3",
      "externalReferences": [
        {
          "url": "https://musl.libc.org/",
          "type": "distribution"
        }
      ],
      "properties": [
        {
          "name": "syft:package:foundBy",
          "value": "apk-db-cataloger"
        },
        {
          "name": "syft:package:type",
          "value": "apk"
        },
        {
          "name": "syft:package:metadataType",
          "value": "apk-db-entry"
        },
        {
          "name": "syft:cpe23",
          "value": "cpe:2.3:a:musl_libc:musl:1.2.5-r9:*:*:*:*:*:*:*"
        },
        {
          "name": "syft:cpe23",
          "value": "cpe:2.3:a:musl:musl:1.2.5-r9:*:*:*:*:*:*:*"
        },
        {
          "name": "syft:location:0:layerID",
          "value": "sha256:a16e98724c05975ee8c40d8fe389c3481373d34ab20a1cf52ea2accc43f71f4c"
        },
        {
          "name": "syft:location:0:path",
          "value": "/lib/apk/db/installed"
        },
        {
          "name": "syft:metadata:gitCommitOfApkPort",
          "value": "efd4d5df7be0ea48d98512671f676fc5ceb14899"
        },
        {
          "name": "syft:metadata:installedSize",
          "value": "723480"
        },
        {
          "name": "syft:metadata:originPackage",
          "value": "musl"
        },
        {
          "name": "syft:metadata:provides:0",
          "value": "so:libc.musl-aarch64.so.1=1"
        },
        {
          "name": "syft:metadata:pullChecksum",
          "value": "Q1b9f8KH7RJnBrrbyrGSaTf0V8v5I="
        },
        {
          "name": "syft:metadata:size",
          "value": "417357"
        }
      ]
    },
    {
      "bom-ref": "pkg:apk/alpine/musl-utils@1.2.5-r9?arch=aarch64&distro=alpine-3.21.3&package-id=81a17879d8c02d3e&upstream=musl",
      "type": "library",
      "publisher": "Natanael Copa <ncopa@alpinelinux.org>",
      "name": "musl-utils",
      "version": "1.2.5-r9",
      "description": "the musl c library (libc) implementation",
      "licenses": [
        {
          "expression": "MIT AND BSD-2-Clause AND GPL-2.0-or-later"
        }
      ],
      "cpe": "cpe:2.3:a:musl-utils:musl-utils:1.2.5-r9:*:*:*:*:*:*:*",
      "purl": "pkg:apk/alpine/musl-utils@1.2.5-r9?arch=aarch64&distro=alpine-3.21.3&upstream=musl",
      "externalReferences": [
        {
          "url": "https://musl.libc.org/",
          "type": "distribution"
        }
      ],
      "properties": [
        {
          "name": "syft:package:foundBy",
          "value": "apk-db-cataloger"
        },
        {
          "name": "syft:package:type",
          "value": "apk"
        },
        {
          "name": "syft:package:metadataType",
          "value": "apk-db-entry"
        },
        {
          "name": "syft:cpe23",
          "value": "cpe:2.3:a:musl-utils:musl_utils:1.2.5-r9:*:*:*:*:*:*:*"
        },
        {
          "name": "syft:cpe23",
          "value": "cpe:2.3:a:musl_utils:musl-utils:1.2.5-r9:*:*:*:*:*:*:*"
        },
        {
          "name": "syft:cpe23",
          "value": "cpe:2.3:a:musl_utils:musl_utils:1.2.5-r9:*:*:*:*:*:*:*"
        },
        {
          "name": "syft:cpe23",
          "value": "cpe:2.3:a:musl-libc:musl-utils:1.2.5-r9:*:*:*:*:*:*:*"
        },
        {
          "name": "syft:cpe23",
          "value": "cpe:2.3:a:musl-libc:musl_utils:1.2.5-r9:*:*:*:*:*:*:*"
        },
        {
          "name": "syft:cpe23",
          "value": "cpe:2.3:a:musl:musl-utils:1.2.5-r9:*:*:*:*:*:*:*"
        },
        {
          "name": "syft:cpe23",
          "value": "cpe:2.3:a:musl:musl_utils:1.2.5-r9:*:*:*:*:*:*:*"
        },
        {
          "name": "syft:location:0:layerID",
          "value": "sha256:a16e98724c05975ee8c40d8fe389c3481373d34ab20a1cf52ea2accc43f71f4c"
        },
        {
          "name": "syft:location:0:path",
          "value": "/lib/apk/db/installed"
        },
        {
          "name": "syft:metadata:gitCommitOfApkPort",
          "value": "efd4d5df7be0ea48d98512671f676fc5ceb14899"
        },
        {
          "name": "syft:metadata:installedSize",
          "value": "256550"
        },
        {
          "name": "syft:metadata:originPackage",
          "value": "musl"
        },
        {
          "name": "syft:metadata:provides:0",
          "value": "libc-utils=1.2.5-r9"
        },
        {
          "name": "syft:metadata:provides:1",
          "value": "cmd:getconf=1.2.5-r9"
        },
        {
          "name": "syft:metadata:provides:2",
          "value": "cmd:getent=1.2.5-r9"
        },
        {
          "name": "syft:metadata:provides:3",
          "value": "cmd:iconv=1.2.5-r9"
        },
        {
          "name": "syft:metadata:provides:4",
          "value": "cmd:ldconfig=1.2.5-r9"
        },
        {
          "name": "syft:metadata:provides:5",
          "value": "cmd:ldd=1.2.5-r9"
        },
        {
          "name": "syft:metadata:pullChecksum",
          "value": "Q15J7iCIth3ZC+GVb2dQjVPpi8Rjo="
        },
        {
          "name": "syft:metadata:pullDependencies:0",
          "value": "scanelf"
        },
        {
          "name": "syft:metadata:pullDependencies:1",
          "value": "so:libc.musl-aarch64.so.1"
        },
        {
          "name": "syft:metadata:size",
          "value": "39143"
        }
      ]
    },
    {
      "bom-ref": "pkg:apk/alpine/scanelf@1.3.8-r1?arch=aarch64&distro=alpine-3.21.3&package-id=1b9f52b034a871af&upstream=pax-utils",
      "type": "library",
      "publisher": "Natanael Copa <ncopa@alpinelinux.org>",
      "name": "scanelf",
      "version": "1.3.8-r1",
      "description": "Scan ELF binaries for stuff",
      "licenses": [
        {
          "license": {
            "id": "GPL-2.0-only"
          }
        }
      ],
      "cpe": "cpe:2.3:a:scanelf:scanelf:1.3.8-r1:*:*:*:*:*:*:*",
      "purl": "pkg:apk/alpine/scanelf@1.3.8-r1?arch=aarch64&distro=alpine-3.21.3&upstream=pax-utils",
      "externalReferences": [
        {
          "url": "https://wiki.gentoo.org/wiki/Hardened/PaX_Utilities",
          "type": "distribution"
        }
      ],
      "properties": [
        {
          "name": "syft:package:foundBy",
          "value": "apk-db-cataloger"
        },
        {
          "name": "syft:package:type",
          "value": "apk"
        },
        {
          "name": "syft:package:metadataType",
          "value": "apk-db-entry"
        },
        {
          "name": "syft:location:0:layerID",
          "value": "sha256:a16e98724c05975ee8c40d8fe389c3481373d34ab20a1cf52ea2accc43f71f4c"
        },
        {
          "name": "syft:location:0:path",
          "value": "/lib/apk/db/installed"
        },
        {
          "name": "syft:metadata:gitCommitOfApkPort",
          "value": "398a5aee3025ec8a4d0d761e448dc86ac777fa09"
        },
        {
          "name": "syft:metadata:installedSize",
          "value": "67424"
        },
        {
          "name": "syft:metadata:originPackage",
          "value": "pax-utils"
        },
        {
          "name": "syft:metadata:provides:0",
          "value": "cmd:scanelf=1.3.8-r1"
        },
        {
          "name": "syft:metadata:pullChecksum",
          "value": "Q1wtXOtXltlxMn8m9w3LuCiDFGGQY="
        },
        {
          "name": "syft:metadata:pullDependencies:0",
          "value": "so:libc.musl-aarch64.so.1"
        },
        {
          "name": "syft:metadata:size",
          "value": "31813"
        }
      ]
    },
    {
      "bom-ref": "pkg:apk/alpine/ssl_client@1.37.0-r12?arch=aarch64&distro=alpine-3.21.3&package-id=03edcc07df915444&upstream=busybox",
      "type": "library",
      "publisher": "Sören Tempel <soeren+alpine@soeren-tempel.net>",
      "name": "ssl_client",
      "version": "1.37.0-r12",
      "description": "External ssl_client for busybox wget",
      "licenses": [
        {
          "license": {
            "id": "GPL-2.0-only"
          }
        }
      ],
      "cpe": "cpe:2.3:a:ssl-client:ssl-client:1.37.0-r12:*:*:*:*:*:*:*",
      "purl": "pkg:apk/alpine/ssl_client@1.37.0-r12?arch=aarch64&distro=alpine-3.21.3&upstream=busybox",
      "externalReferences": [
        {
          "url": "https://busybox.net/",
          "type": "distribution"
        }
      ],
      "properties": [
        {
          "name": "syft:package:foundBy",
          "value": "apk-db-cataloger"
        },
        {
          "name": "syft:package:type",
          "value": "apk"
        },
        {
          "name": "syft:package:metadataType",
          "value": "apk-db-entry"
        },
        {
          "name": "syft:cpe23",
          "value": "cpe:2.3:a:ssl-client:ssl_client:1.37.0-r12:*:*:*:*:*:*:*"
        },
        {
          "name": "syft:cpe23",
          "value": "cpe:2.3:a:ssl_client:ssl-client:1.37.0-r12:*:*:*:*:*:*:*"
        },
        {
          "name": "syft:cpe23",
          "value": "cpe:2.3:a:ssl_client:ssl_client:1.37.0-r12:*:*:*:*:*:*:*"
        },
        {
          "name": "syft:cpe23",
          "value": "cpe:2.3:a:ssl:ssl-client:1.37.0-r12:*:*:*:*:*:*:*"
        },
        {
          "name": "syft:cpe23",
          "value": "cpe:2.3:a:ssl:ssl_client:1.37.0-r12:*:*:*:*:*:*:*"
        },
        {
          "name": "syft:location:0:layerID",
          "value": "sha256:a16e98724c05975ee8c40d8fe389c3481373d34ab20a1cf52ea2accc43f71f4c"
        },
        {
          "name": "syft:location:0:path",
          "value": "/lib/apk/db/installed"
        },
        {
          "name": "syft:metadata:gitCommitOfApkPort",
          "value": "9c49608930ef6a9936750e9e39edec56b3db9cd5"
        },
        {
          "name": "syft:metadata:installedSize",
          "value": "67472"
        },
        {
          "name": "syft:metadata:originPackage",
          "value": "busybox"
        },
        {
          "name": "syft:metadata:provides:0",
          "value": "cmd:ssl_client=1.37.0-r12"
        },
        {
          "name": "syft:metadata:pullChecksum",
          "value": "Q1Vf152/NhxT0U+MgLHROvUpE0Esw="
        },
        {
          "name": "syft:metadata:pullDependencies:0",
          "value": "so:libc.musl-aarch64.so.1"
        },
        {
          "name": "syft:metadata:pullDependencies:1",
          "value": "so:libcrypto.so.3"
        },
        {
          "name": "syft:metadata:pullDependencies:2",
          "value": "so:libssl.so.3"
        },
        {
          "name": "syft:metadata:size",
          "value": "5018"
        }
      ]
    },
    {
      "bom-ref": "pkg:apk/alpine/zlib@1.3.1-r2?arch=aarch64&distro=alpine-3.21.3&package-id=481fe018ff83ae8d",
      "type": "library",
      "publisher": "Natanael Copa <ncopa@alpinelinux.org>",
      "name": "zlib",
      "version": "1.3.1-r2",
      "description": "A compression/decompression Library",
      "licenses": [
        {
          "license": {
            "id": "Zlib"
          }
        }
      ],
      "cpe": "cpe:2.3:a:zlib:zlib:1.3.1-r2:*:*:*:*:*:*:*",
      "purl": "pkg:apk/alpine/zlib@1.3.1-r2?arch=aarch64&distro=alpine-3.21.3",
      "externalReferences": [
        {
          "url": "https://zlib.net/",
          "type": "distribution"
        }
      ],
      "properties": [
        {
          "name": "syft:package:foundBy",
          "value": "apk-db-cataloger"
        },
        {
          "name": "syft:package:type",
          "value": "apk"
        },
        {
          "name": "syft:package:metadataType",
          "value": "apk-db-entry"
        },
        {
          "name": "syft:location:0:layerID",
          "value": "sha256:a16e98724c05975ee8c40d8fe389c3481373d34ab20a1cf52ea2accc43f71f4c"
        },
        {
          "name": "syft:location:0:path",
          "value": "/lib/apk/db/installed"
        },
        {
          "name": "syft:metadata:gitCommitOfApkPort",
          "value": "4c2722e7ecc1c5e3ba882429044a101497121223"
        },
        {
          "name": "syft:metadata:installedSize",
          "value": "133008"
        },
        {
          "name": "syft:metadata:originPackage",
          "value": "zlib"
        },
        {
          "name": "syft:metadata:provides:0",
          "value": "so:libz.so.1=1.3.1"
        },
        {
          "name": "syft:metadata:pullChecksum",
          "value": "Q1ZEtAcwgZopzoL/lwkvjL8KcMEVo="
        },
        {
          "name": "syft:metadata:pullDependencies:0",
          "value": "so:libc.musl-aarch64.so.1"
        },
        {
          "name": "syft:metadata:size",
          "value": "52823"
        }
      ]
    },
    {
      "bom-ref": "os:alpine@3.21.3",
      "type": "operating-system",
      "name": "alpine",
      "version": "3.21.3",
      "description": "Alpine Linux v3.21",
      "swid": {
        "tagId": "alpine",
        "name": "alpine",
        "version": "3.21.3"
      },
      "externalReferences": [
        {
          "url": "https://gitlab.alpinelinux.org/alpine/aports/-/issues",
          "type": "issue-tracker"
        },
        {
          "url": "https://alpinelinux.org/",
          "type": "website"
        }
      ],
      "properties": [
        {
          "name": "syft:distro:id",
          "value": "alpine"
        },
        {
          "name": "syft:distro:idLike:0",
          "value": "alpine"
        },
        {
          "name": "syft:distro:prettyName",
          "value": "Alpine Linux v3.21"
        },
        {
          "name": "syft:distro:versionID",
          "value": "3.21.3"
        }
      ]
    }
  ],
  "dependencies": [
    {
      "ref": "pkg:apk/alpine/alpine-baselayout@3.6.8-r1?arch=aarch64&distro=alpine-3.21.3&package-id=eb172957096b5fad",
      "dependsOn": [
        "pkg:apk/alpine/alpine-baselayout-data@3.6.8-r1?arch=aarch64&distro=alpine-3.21.3&package-id=310baff175e0e857&upstream=alpine-baselayout",
        "pkg:apk/alpine/busybox-binsh@1.37.0-r12?arch=aarch64&distro=alpine-3.21.3&package-id=48085e7886725464&upstream=busybox"
      ]
    },
    {
      "ref": "pkg:apk/alpine/alpine-release@3.21.3-r0?arch=aarch64&distro=alpine-3.21.3&package-id=c2770f4444533708&upstream=alpine-base",
      "dependsOn": [
        "pkg:apk/alpine/alpine-keys@2.5-r0?arch=aarch64&distro=alpine-3.21.3&package-id=735292f63d85ad1b"
      ]
    },
    {
      "ref": "pkg:apk/alpine/apk-tools@2.14.6-r3?arch=aarch64&distro=alpine-3.21.3&package-id=34599c1544d9cb19",
      "dependsOn": [
        "pkg:apk/alpine/ca-certificates-bundle@20241121-r1?arch=aarch64&distro=alpine-3.21.3&package-id=c220c2f0a7efb6df&upstream=ca-certificates",
        "pkg:apk/alpine/libcrypto3@3.3.3-r0?arch=aarch64&distro=alpine-3.21.3&package-id=de0a6f96a830ce94&upstream=openssl",
        "pkg:apk/alpine/libssl3@3.3.3-r0?arch=aarch64&distro=alpine-3.21.3&package-id=9863a120116129b2&upstream=openssl",
        "pkg:apk/alpine/musl@1.2.5-r9?arch=aarch64&distro=alpine-3.21.3&package-id=462870b7d92984af",
        "pkg:apk/alpine/zlib@1.3.1-r2?arch=aarch64&distro=alpine-3.21.3&package-id=481fe018ff83ae8d"
      ]
    },
    {
      "ref": "pkg:apk/alpine/busybox-binsh@1.37.0-r12?arch=aarch64&distro=alpine-3.21.3&package-id=48085e7886725464&upstream=busybox",
      "dependsOn": [
        "pkg:apk/alpine/busybox@1.37.0-r12?arch=aarch64&distro=alpine-3.21.3&package-id=59022883e79a5e6e"
      ]
    },
    {
      "ref": "pkg:apk/alpine/busybox@1.37.0-r12?arch=aarch64&distro=alpine-3.21.3&package-id=59022883e79a5e6e",
      "dependsOn": [
        "pkg:apk/alpine/musl@1.2.5-r9?arch=aarch64&distro=alpine-3.21.3&package-id=462870b7d92984af"
      ]
    },
    {
      "ref": "pkg:apk/alpine/libcrypto3@3.3.3-r0?arch=aarch64&distro=alpine-3.21.3&package-id=de0a6f96a830ce94&upstream=openssl",
      "dependsOn": [
        "pkg:apk/alpine/musl@1.2.5-r9?arch=aarch64&distro=alpine-3.21.3&package-id=462870b7d92984af"
      ]
    },
    {
      "ref": "pkg:apk/alpine/libssl3@3.3.3-r0?arch=aarch64&distro=alpine-3.21.3&package-id=9863a120116129b2&upstream=openssl",
      "dependsOn": [
        "pkg:apk/alpine/libcrypto3@3.3.3-r0?arch=aarch64&distro=alpine-3.21.3&package-id=de0a6f96a830ce94&upstream=openssl",
        "pkg:apk/alpine/musl@1.2.5-r9?arch=aarch64&distro=alpine-3.21.3&package-id=462870b7d92984af"
      ]
    },
    {
      "ref": "pkg:apk/alpine/musl-utils@1.2.5-r9?arch=aarch64&distro=alpine-3.21.3&package-id=81a17879d8c02d3e&upstream=musl",
      "dependsOn": [
        "pkg:apk/alpine/musl@1.2.5-r9?arch=aarch64&distro=alpine-3.21.3&package-id=462870b7d92984af",
        "pkg:apk/alpine/scanelf@1.3.8-r1?arch=aarch64&distro=alpine-3.21.3&package-id=1b9f52b034a871af&upstream=pax-utils"
      ]
    },
    {
      "ref": "pkg:apk/alpine/scanelf@1.3.8-r1?arch=aarch64&distro=alpine-3.21.3&package-id=1b9f52b034a871af&upstream=pax-utils",
      "dependsOn": [
        "pkg:apk/alpine/musl@1.2.5-r9?arch=aarch64&distro=alpine-3.21.3&package-id=462870b7d92984af"
      ]
    },
    {
      "ref": "pkg:apk/alpine/ssl_client@1.37.0-r12?arch=aarch64&distro=alpine-3.21.3&package-id=03edcc07df915444&upstream=busybox",
      "dependsOn": [
        "pkg:apk/alpine/libcrypto3@3.3.3-r0?arch=aarch64&distro=alpine-3.21.3&package-id=de0a6f96a830ce94&upstream=openssl",
        "pkg:apk/alpine/libssl3@3.3.3-r0?arch=aarch64&distro=alpine-3.21.3&package-id=9863a120116129b2&upstream=openssl",
        "pkg:apk/alpine/musl@1.2.5-r9?arch=aarch64&distro=alpine-3.21.3&package-id=462870b7d92984af"
      ]
    },
    {
      "ref": "pkg:apk/alpine/zlib@1.3.1-r2?arch=aarch64&distro=alpine-3.21.3&package-id=481fe018ff83ae8d",
      "dependsOn": [
        "pkg:apk/alpine/musl@1.2.5-r9?arch=aarch64&distro=alpine-3.21.3&package-id=462870b7d92984af"
      ]
    }
  ],
  "vulnerabilities": [
    {
      "bom-ref": "urn:uuid:a47ce701-81aa-4f3f-b0e7-f72bb255d506",
      "id": "CVE-2024-58251",
      "source": {
        "name": "nvd-cpe",
        "url": "https://nvd.nist.gov/vuln/detail/CVE-2024-58251"
      },
      "references": [
        {
          "id": "CVE-2024-58251",
          "source": {
            "name": "nvd-cpe",
            "url": "https://nvd.nist.gov/vuln/detail/CVE-2024-58251"
          }
        }
      ],
      "ratings": [
        {
          "score": 2.5,
          "severity": "low",
          "method": "CVSSv31",
          "vector": "CVSS:3.1/AV:L/AC:H/PR:N/UI:R/S:U/C:N/I:N/A:L"
        }
      ],
      "description": "In netstat in BusyBox through 1.37.0, local users can launch of network application with an argv[0] containing an ANSI terminal escape sequence, leading to a denial of service (terminal locked up) when netstat is used by a victim.",
      "advisories": [
        {
          "url": "https://bugs.busybox.net/show_bug.cgi?id=15922"
        },
        {
          "url": "https://www.busybox.net"
        },
        {
          "url": "https://www.busybox.net/downloads/"
        },
        {
          "url": "http://www.openwall.com/lists/oss-security/2025/04/23/6"
        }
      ],
      "affects": [
        {
          "ref": "pkg:apk/alpine/busybox@1.37.0-r12?arch=aarch64&distro=alpine-3.21.3&package-id=59022883e79a5e6e"
        }
      ]
    },
    {
      "bom-ref": "urn:uuid:2a15e1d1-937d-47a7-8dfa-1807d970a543",
      "id": "CVE-2025-46394",
      "source": {
        "name": "nvd-cpe",
        "url": "https://nvd.nist.gov/vuln/detail/CVE-2025-46394"
      },
      "references": [
        {
          "id": "CVE-2025-46394",
          "source": {
            "name": "nvd-cpe",
            "url": "https://nvd.nist.gov/vuln/detail/CVE-2025-46394"
          }
        }
      ],
      "ratings": [
        {
          "score": 3.2,
          "severity": "low",
          "method": "CVSSv31",
          "vector": "CVSS:3.1/AV:L/AC:H/PR:N/UI:N/S:C/C:N/I:L/A:N"
        }
      ],
      "description": "In tar in BusyBox through 1.37.0, a TAR archive can have filenames hidden from a listing through the use of terminal escape sequences.",
      "advisories": [
        {
          "url": "https://bugs.busybox.net/show_bug.cgi?id=16018"
        },
        {
          "url": "https://www.busybox.net"
        },
        {
          "url": "https://www.busybox.net/downloads/"
        },
        {
          "url": "http://www.openwall.com/lists/oss-security/2025/04/23/5"
        },
        {
          "url": "http://www.openwall.com/lists/oss-security/2025/04/24/3"
        }
      ],
      "affects": [
        {
          "ref": "pkg:apk/alpine/busybox@1.37.0-r12?arch=aarch64&distro=alpine-3.21.3&package-id=59022883e79a5e6e"
        }
      ]
    },
    {
      "bom-ref": "urn:uuid:f41bcdc9-a864-422c-9056-6c8916f6c9a2",
      "id": "CVE-2024-58251",
      "source": {
        "name": "nvd-cpe",
        "url": "https://nvd.nist.gov/vuln/detail/CVE-2024-58251"
      },
      "references": [
        {
          "id": "CVE-2024-58251",
          "source": {
            "name": "nvd-cpe",
            "url": "https://nvd.nist.gov/vuln/detail/CVE-2024-58251"
          }
        }
      ],
      "ratings": [
        {
          "score": 2.5,
          "severity": "low",
          "method": "CVSSv31",
          "vector": "CVSS:3.1/AV:L/AC:H/PR:N/UI:R/S:U/C:N/I:N/A:L"
        }
      ],
      "description": "In netstat in BusyBox through 1.37.0, local users can launch of network application with an argv[0] containing an ANSI terminal escape sequence, leading to a denial of service (terminal locked up) when netstat is used by a victim.",
      "advisories": [
        {
          "url": "https://bugs.busybox.net/show_bug.cgi?id=15922"
        },
        {
          "url": "https://www.busybox.net"
        },
        {
          "url": "https://www.busybox.net/downloads/"
        },
        {
          "url": "http://www.openwall.com/lists/oss-security/2025/04/23/6"
        }
      ],
      "affects": [
        {
          "ref": "pkg:apk/alpine/busybox-binsh@1.37.0-r12?arch=aarch64&distro=alpine-3.21.3&package-id=48085e7886725464&upstream=busybox"
        }
      ]
    },
    {
      "bom-ref": "urn:uuid:60e8597f-7720-4aaa-a040-baf90694b5fd",
      "id": "CVE-2025-46394",
      "source": {
        "name": "nvd-cpe",
        "url": "https://nvd.nist.gov/vuln/detail/CVE-2025-46394"
      },
      "references": [
        {
          "id": "CVE-2025-46394",
          "source": {
            "name": "nvd-cpe",
            "url": "https://nvd.nist.gov/vuln/detail/CVE-2025-46394"
          }
        }
      ],
      "ratings": [
        {
          "score": 3.2,
          "severity": "low",
          "method": "CVSSv31",
          "vector": "CVSS:3.1/AV:L/AC:H/PR:N/UI:N/S:C/C:N/I:L/A:N"
        }
      ],
      "description": "In tar in BusyBox through 1.37.0, a TAR archive can have filenames hidden from a listing through the use of terminal escape sequences.",
      "advisories": [
        {
          "url": "https://bugs.busybox.net/show_bug.cgi?id=16018"
        },
        {
          "url": "https://www.busybox.net"
        },
        {
          "url": "https://www.busybox.net/downloads/"
        },
        {
          "url": "http://www.openwall.com/lists/oss-security/2025/04/23/5"
        },
        {
          "url": "http://www.openwall.com/lists/oss-security/2025/04/24/3"
        }
      ],
      "affects": [
        {
          "ref": "pkg:apk/alpine/busybox-binsh@1.37.0-r12?arch=aarch64&distro=alpine-3.21.3&package-id=48085e7886725464&upstream=busybox"
        }
      ]
    },
    {
      "bom-ref": "urn:uuid:b5062629-db7f-4910-af3c-b93d8c8e8d50",
      "id": "CVE-2024-58251",
      "source": {
        "name": "nvd-cpe",
        "url": "https://nvd.nist.gov/vuln/detail/CVE-2024-58251"
      },
      "references": [
        {
          "id": "CVE-2024-58251",
          "source": {
            "name": "nvd-cpe",
            "url": "https://nvd.nist.gov/vuln/detail/CVE-2024-58251"
          }
        }
      ],
      "ratings": [
        {
          "score": 2.5,
          "severity": "low",
          "method": "CVSSv31",
          "vector": "CVSS:3.1/AV:L/AC:H/PR:N/UI:R/S:U/C:N/I:N/A:L"
        }
      ],
      "description": "In netstat in BusyBox through 1.37.0, local users can launch of network application with an argv[0] containing an ANSI terminal escape sequence, leading to a denial of service (terminal locked up) when netstat is used by a victim.",
      "advisories": [
        {
          "url": "https://bugs.busybox.net/show_bug.cgi?id=15922"
        },
        {
          "url": "https://www.busybox.net"
        },
        {
          "url": "https://www.busybox.net/downloads/"
        },
        {
          "url": "http://www.openwall.com/lists/oss-security/2025/04/23/6"
        }
      ],
      "affects": [
        {
          "ref": "pkg:apk/alpine/ssl_client@1.37.0-r12?arch=aarch64&distro=alpine-3.21.3&package-id=03edcc07df915444&upstream=busybox"
        }
      ]
    },
    {
      "bom-ref": "urn:uuid:b381819e-c123-4dd9-8b1c-ded8beccbd6a",
      "id": "CVE-2025-46394",
      "source": {
        "name": "nvd-cpe",
        "url": "https://nvd.nist.gov/vuln/detail/CVE-2025-46394"
      },
      "references": [
        {
          "id": "CVE-2025-46394",
          "source": {
            "name": "nvd-cpe",
            "url": "https://nvd.nist.gov/vuln/detail/CVE-2025-46394"
          }
        }
      ],
      "ratings": [
        {
          "score": 3.2,
          "severity": "low",
          "method": "CVSSv31",
          "vector": "CVSS:3.1/AV:L/AC:H/PR:N/UI:N/S:C/C:N/I:L/A:N"
        }
      ],
      "description": "In tar in BusyBox through 1.37.0, a TAR archive can have filenames hidden from a listing through the use of terminal escape sequences.",
      "advisories": [
        {
          "url": "https://bugs.busybox.net/show_bug.cgi?id=16018"
        },
        {
          "url": "https://www.busybox.net"
        },
        {
          "url": "https://www.busybox.net/downloads/"
        },
        {
          "url": "http://www.openwall.com/lists/oss-security/2025/04/23/5"
        },
        {
          "url": "http://www.openwall.com/lists/oss-security/2025/04/24/3"
        }
      ],
      "affects": [
        {
          "ref": "pkg:apk/alpine/ssl_client@1.37.0-r12?arch=aarch64&distro=alpine-3.21.3&package-id=03edcc07df915444&upstream=busybox"
        }
      ]
    }
  ]
}
